{
  "globals": {
    "colors": {
      "blue": {
        "50": {
          "type": "color",
          "value": "#f0f6ff"
        },
        "100": {
          "type": "color",
          "value": "#deebfc"
        },
        "200": {
          "type": "color",
          "value": "#8ab6f4"
        },
        "300": {
          "type": "color",
          "value": "#478beb"
        },
        "400": {
          "type": "color",
          "value": "#2265c3"
        },
        "500": {
          "type": "color",
          "value": "#1b447e"
        },
        "alpha": {
          "20090": {
            "type": "color",
            "value": "rgba(138, 182, 244, 0.9000)"
          },
          "30030": {
            "type": "color",
            "value": "rgba(71, 139, 235, 0.3000)"
          }
        }
      },
      "green": {
        "50": {
          "type": "color",
          "value": "#f3fcf6"
        },
        "100": {
          "type": "color",
          "value": "#d5f6e1"
        },
        "200": {
          "type": "color",
          "value": "#a3ebbc"
        },
        "300": {
          "type": "color",
          "value": "#53d580"
        },
        "400": {
          "type": "color",
          "value": "#419b5f"
        },
        "500": {
          "type": "color",
          "value": "#326c44"
        },
        "alpha": {
          "20080": {
            "type": "color",
            "value": "rgba(163, 235, 188, 0.8000)"
          },
          "30030": {
            "type": "color",
            "value": "rgba(83, 213, 128, 0.3000)"
          },
          "30050": {
            "type": "color",
            "value": "rgba(83, 213, 128, 0.5000)"
          }
        }
      },
      "red": {
        "50": {
          "type": "color",
          "value": "#fee7e7"
        },
        "100": {
          "type": "color",
          "value": "#fccfcf"
        },
        "200": {
          "type": "color",
          "value": "#f78787"
        },
        "300": {
          "type": "color",
          "value": "#f34949"
        },
        "400": {
          "type": "color",
          "value": "#c41212"
        },
        "500": {
          "type": "color",
          "value": "#911212"
        },
        "alpha": {
          "20090": {
            "type": "color",
            "value": "rgba(247, 135, 135, 0.9000)"
          },
          "30030": {
            "type": "color",
            "value": "rgba(243, 73, 73, 0.3000)"
          }
        }
      },
      "yellow": {
        "50": {
          "type": "color",
          "value": "#fffbeb"
        },
        "100": {
          "type": "color",
          "value": "#fdf4c4"
        },
        "200": {
          "type": "color",
          "value": "#fbe58e"
        },
        "300": {
          "type": "color",
          "value": "#f8d330"
        },
        "400": {
          "type": "color",
          "value": "#d1ad0a"
        },
        "500": {
          "type": "color",
          "value": "#77620d"
        },
        "alpha": {
          "20090": {
            "type": "color",
            "value": "rgba(251, 229, 142, 0.9000)"
          },
          "30030": {
            "type": "color",
            "value": "rgba(248, 211, 48, 0.3000)"
          }
        }
      }
    },
    "numbers": {
      "border-radius": {
        "radius-0": {
          "type": "number",
          "value": 0
        },
        "radius-10": {
          "type": "number",
          "value": 10
        },
        "radius-12": {
          "type": "number",
          "value": 12
        },
        "radius-16": {
          "type": "number",
          "value": 16
        },
        "radius-2": {
          "type": "number",
          "value": 8
        },
        "radius-20": {
          "type": "number",
          "value": 20
        },
        "radius-24": {
          "type": "number",
          "value": 24
        },
        "radius-4": {
          "type": "number",
          "value": 4
        },
        "radius-6": {
          "type": "number",
          "value": 6
        },
        "radius-8": {
          "type": "number",
          "value": 8
        },
        "radius-full": {
          "type": "number",
          "value": 9999
        }
      },
      "screen-size": {
        "width-2xl": {
          "type": "number",
          "value": 1024
        },
        "width-3xl": {
          "type": "number",
          "value": 1280
        },
        "width-4xl": {
          "type": "number",
          "value": 1440
        },
        "width-5xl": {
          "type": "number",
          "value": 1600
        },
        "width-6xl": {
          "type": "number",
          "value": 1920
        },
        "width-lg": {
          "type": "number",
          "value": 640
        },
        "width-md": {
          "type": "number",
          "value": 560
        },
        "width-sm": {
          "type": "number",
          "value": 480
        },
        "width-xl": {
          "type": "number",
          "value": 768
        },
        "width-xs": {
          "type": "number",
          "value": 384
        },
        "width-xxs": {
          "type": "number",
          "value": 320
        }
      },
      "spacing": {
        "spacing-0": {
          "type": "number",
          "value": 0
        },
        "spacing-12": {
          "type": "number",
          "value": 12
        },
        "spacing-128": {
          "type": "number",
          "value": 128
        },
        "spacing-16": {
          "type": "number",
          "value": 16
        },
        "spacing-160": {
          "type": "number",
          "value": 160
        },
        "spacing-2": {
          "type": "number",
          "value": 2
        },
        "spacing-20": {
          "type": "number",
          "value": 20
        },
        "spacing-24": {
          "type": "number",
          "value": 24
        },
        "spacing-32": {
          "type": "number",
          "value": 32
        },
        "spacing-4": {
          "type": "number",
          "value": 4
        },
        "spacing-40": {
          "type": "number",
          "value": 40
        },
        "spacing-48": {
          "type": "number",
          "value": 48
        },
        "spacing-6": {
          "type": "number",
          "value": 6
        },
        "spacing-64": {
          "type": "number",
          "value": 64
        },
        "spacing-8": {
          "type": "number",
          "value": 8
        },
        "spacing-80": {
          "type": "number",
          "value": 80
        },
        "spacing-96": {
          "type": "number",
          "value": 96
        }
      }
    },
    "typography": {
      "font-size": {
        "body-1": {
          "type": "number",
          "value": 16
        },
        "body-2": {
          "type": "number",
          "value": 14
        },
        "body-3": {
          "type": "number",
          "value": 12
        },
        "button-lg": {
          "type": "number",
          "value": 18
        },
        "button-md": {
          "type": "number",
          "value": 16
        },
        "button-sm": {
          "type": "number",
          "value": 14
        },
        "caption": {
          "type": "number",
          "value": 10
        },
        "display": {
          "type": "number",
          "value": 74
        },
        "heading-1": {
          "type": "number",
          "value": 48
        },
        "heading-2": {
          "type": "number",
          "value": 32
        },
        "headling-3": {
          "type": "number",
          "value": 24
        },
        "headling-4": {
          "type": "number",
          "value": 20
        },
        "headling-5": {
          "type": "number",
          "value": 18
        },
        "overline": {
          "type": "number",
          "value": 10
        }
      },
      "font-weight": {
        "bold": {
          "type": "number",
          "value": 700
        },
        "light": {
          "type": "number",
          "value": 300
        },
        "regular": {
          "type": "number",
          "value": 400
        },
        "semibold": {
          "type": "number",
          "value": 600
        }
      },
      "letter-spacing": {
        "normal": {
          "type": "number",
          "value": 0
        },
        "tight": {
          "type": "number",
          "value": -0.25
        },
        "tighter": {
          "type": "number",
          "value": -0.5
        },
        "tightest": {
          "type": "number",
          "value": -1.5
        },
        "wide": {
          "type": "number",
          "value": 0.25
        },
        "wider": {
          "type": "number",
          "value": 0.5
        },
        "widest": {
          "type": "number",
          "value": 1
        }
      }
    }
  },
  "brand": {
    "colors": {
      "brand": {
        "accent1": {
          "1002": {
            "type": "color",
            "value": "#bad9d5"
          },
          "2002": {
            "type": "color",
            "value": "#7fb8b2"
          },
          "3002": {
            "type": "color",
            "value": "#5ea69e"
          },
          "4002": {
            "type": "color",
            "value": "#4b867f"
          },
          "5002": {
            "type": "color",
            "value": "#3a645f"
          }
        },
        "accent2": {
          "100": {
            "type": "color",
            "value": "#fef0d8"
          },
          "200": {
            "type": "color",
            "value": "#fcdda6"
          },
          "300": {
            "type": "color",
            "value": "#fac974"
          },
          "400": {
            "type": "color",
            "value": "#f8b644"
          },
          "500": {
            "type": "color",
            "value": "#f7a313"
          }
        },
        "gradients": {
          "gradient-from": {
            "type": "color",
            "value": "#bd1f2e"
          },
          "gradient-to": {
            "type": "color",
            "value": "#882059"
          }
        },
        "primary": {
          "100": {
            "type": "color",
            "value": "#cb7c82"
          },
          "200": {
            "type": "color",
            "value": "#b95059"
          },
          "300": {
            "type": "color",
            "value": "#a8242f"
          },
          "400": {
            "type": "color",
            "value": "#861d26"
          },
          "500": {
            "type": "color",
            "value": "#64161d"
          },
          "alpha": {
            "0": {
              "type": "color",
              "value": "rgba(168, 36, 47, 0.0000)"
            },
            "1": {
              "type": "color",
              "value": "rgba(168, 36, 47, 0.0100)"
            },
            "5": {
              "type": "color",
              "value": "rgba(168, 36, 47, 0.0500)"
            },
            "10": {
              "type": "color",
              "value": "rgba(168, 36, 47, 0.1000)"
            },
            "20": {
              "type": "color",
              "value": "rgba(168, 36, 47, 0.2000)"
            },
            "90": {
              "type": "color",
              "value": "rgba(168, 36, 47, 0.9000)"
            }
          }
        },
        "secondary": {
          "100": {
            "type": "color",
            "value": "#7f9aa3"
          },
          "200": {
            "type": "color",
            "value": "#546f7a"
          },
          "300": {
            "type": "color",
            "value": "#294350"
          },
          "400": {
            "type": "color",
            "value": "#223944"
          },
          "500": {
            "type": "color",
            "value": "#19282f"
          }
        }
      },
      "neutral": {
        "50": {
          "type": "color",
          "value": "#f3f5f7"
        },
        "100": {
          "type": "color",
          "value": "#e6ebf0"
        },
        "200": {
          "type": "color",
          "value": "#d4dfe2"
        },
        "300": {
          "type": "color",
          "value": "#c1ced2"
        },
        "400": {
          "type": "color",
          "value": "#809aa3"
        },
        "500": {
          "type": "color",
          "value": "#587179"
        },
        "600": {
          "type": "color",
          "value": "#2a4451"
        },
        "700": {
          "type": "color",
          "value": "#223944"
        },
        "800": {
          "type": "color",
          "value": "#19282f"
        },
        "900": {
          "type": "color",
          "value": "#10191e"
        },
        "950": {
          "type": "color",
          "value": "#070b0d"
        },
        "alpha": {
          "50": {
            "5": {
              "type": "color",
              "value": "rgba(243, 245, 247, 0.0500)"
            },
            "10": {
              "type": "color",
              "value": "rgba(243, 245, 247, 0.1000)"
            },
            "20": {
              "type": "color",
              "value": "rgba(243, 245, 247, 0.2000)"
            },
            "50": {
              "type": "color",
              "value": "rgba(243, 245, 247, 0.5000)"
            },
            "90": {
              "type": "color",
              "value": "rgba(243, 245, 247, 0.9000)"
            }
          },
          "100": {
            "50": {
              "type": "color",
              "value": "rgba(230, 235, 240, 0.5000)"
            }
          },
          "900": {
            "10": {
              "type": "color",
              "value": "rgba(16, 25, 30, 0.1000)"
            },
            "50": {
              "type": "color",
              "value": "rgba(16, 25, 30, 0.5000)"
            },
            "70": {
              "type": "color",
              "value": "rgba(16, 25, 30, 0.7000)"
            },
            "90": {
              "type": "color",
              "value": "rgba(16, 25, 30, 0.9000)"
            }
          },
          "950": {
            "5": {
              "type": "color",
              "value": "rgba(7, 11, 13, 0.0500)"
            },
            "10": {
              "type": "color",
              "value": "rgba(7, 11, 13, 0.1000)"
            },
            "20": {
              "type": "color",
              "value": "rgba(7, 11, 13, 0.2000)"
            },
            "50": {
              "type": "color",
              "value": "rgba(7, 11, 13, 0.5000)"
            }
          },
          "black": {
            "2": {
              "type": "color",
              "value": "rgba(0, 0, 0, 0.0200)"
            },
            "20": {
              "type": "color",
              "value": "rgba(0, 0, 0, 0.2000)"
            }
          },
          "white": {
            "2": {
              "type": "color",
              "value": "rgba(255, 255, 255, 0.0200)"
            },
            "20": {
              "type": "color",
              "value": "rgba(255, 255, 255, 0.2000)"
            },
            "70": {
              "type": "color",
              "value": "rgba(255, 255, 255, 0.7000)"
            }
          }
        },
        "black": {
          "type": "color",
          "value": "#000000"
        },
        "white": {
          "type": "color",
          "value": "#ffffff"
        }
      }
    },
    "components": {
      "button": {
        "custom": {
          "bg": {
            "type": "color",
            "value": "{bg.tertiary.default}"
          },
          "bg-hover": {
            "type": "color",
            "value": "{bg.tertiary.hover}"
          },
          "fg": {
            "type": "color",
            "value": "{fg.primary.default}"
          }
        },
        "ghost": {
          "bg-hover": {
            "type": "color",
            "value": "{bg.primary.hover}"
          },
          "fg": {
            "type": "color",
            "value": "{fg.primary.default}"
          },
          "fg-hover": {
            "type": "color",
            "value": "{fg.primary.default}"
          }
        },
        "gradient": {
          "bg- hover1": {
            "type": "color",
            "value": "{colors.brand.gradients.gradient-to}"
          },
          "bg- hover2": {
            "type": "color",
            "value": "{colors.brand.gradients.gradient-from}"
          },
          "bg1": {
            "type": "color",
            "value": "{colors.brand.gradients.gradient-from}"
          },
          "bg2": {
            "type": "color",
            "value": "{colors.brand.gradients.gradient-to}"
          },
          "fg": {
            "type": "color",
            "value": "{colors.neutral.white}"
          },
          "fg-hover": {
            "type": "color",
            "value": "{colors.neutral.white}"
          }
        },
        "outlined": {
          "bg": {
            "type": "color",
            "value": "{bg.secondary.default}"
          },
          "bg-hover": {
            "type": "color",
            "value": "{bg.secondary.default}"
          },
          "border": {
            "type": "color",
            "value": "{colors.brand.primary.300}"
          },
          "fg": {
            "type": "color",
            "value": "{colors.brand.primary.300}"
          },
          "fg-hover": {
            "type": "color",
            "value": "{bg.secondary.default}"
          }
        }
      },
      "icons": {
        "feedback": {
          "alert": {
            "type": "color",
            "value": "{colors.red.500}"
          },
          "info": {
            "type": "color",
            "value": "{colors.blue.500}"
          },
          "success": {
            "type": "color",
            "value": "{colors.green.500}"
          },
          "warning": {
            "type": "color",
            "value": "{colors.yellow.500}"
          }
        },
        "primary": {
          "darkmode": {
            "type": "color",
            "value": "{colors.neutral.50}"
          },
          "darkmode-fade": {
            "type": "color",
            "value": "rgba(244, 246, 248, 0.0000)"
          },
          "default": {
            "type": "color",
            "value": "{colors.neutral.950}"
          },
          "default-fade": {
            "type": "color",
            "value": "rgba(9, 14, 17, 0.0000)"
          }
        },
        "secondary": {
          "darkmode": {
            "type": "color",
            "value": "{colors.brand.primary.300}"
          },
          "darkmode-gradient": {
            "type": "color",
            "value": "{colors.brand.primary.alpha.0}"
          },
          "default": {
            "type": "color",
            "value": "{colors.brand.primary.300}"
          },
          "default-fade": {
            "type": "color",
            "value": "{colors.brand.primary.alpha.0}"
          }
        }
      },
      "other": {
        "bg-logo": {
          "type": "color",
          "value": "#ffffff"
        },
        "bg-notification": {
          "type": "color",
          "value": "{colors.brand.primary.300}"
        }
      }
    },
    "settings": {
      "fonts": {
        "font-family": {
          "type": "string",
          "value": "Inter"
        }
      },
      "logic": {
        "buttonprimaryvariant": {
          "type": "string",
          "value": "String value"
        }
      },
      "radius": {
        "button": {
          "type": "number",
          "value": "{numbers.border-radius.radius-full}"
        },
        "input": {
          "type": "number",
          "value": "{numbers.border-radius.radius-8}"
        },
        "lg": {
          "type": "number",
          "value": "{numbers.border-radius.radius-16}"
        },
        "md": {
          "type": "number",
          "value": "{numbers.border-radius.radius-12}"
        },
        "sm": {
          "type": "number",
          "value": "{numbers.border-radius.radius-8}"
        },
        "xl": {
          "type": "number",
          "value": "{numbers.border-radius.radius-20}"
        },
        "xs": {
          "type": "number",
          "value": "{numbers.border-radius.radius-4}"
        },
        "xxl": {
          "type": "number",
          "value": "{numbers.border-radius.radius-24}"
        },
        "xxs": {
          "type": "number",
          "value": "{numbers.border-radius.radius-2}"
        }
      }
    }
  },
  "theme": {
    "light": {
      "bg": {
        "brand": {
          "accent": {
            "type": "color",
            "value": "{colors.brand.secondary.300}"
          },
          "primary": {
            "type": "color",
            "value": "{colors.brand.primary.300}"
          },
          "secondary": {
            "type": "color",
            "value": "{colors.brand.accent1.3002}"
          }
        },
        "disabled": {
          "primary": {
            "type": "color",
            "value": "{colors.neutral.50}"
          },
          "secondary": {
            "type": "color",
            "value": "{colors.neutral.alpha.900.10}"
          }
        },
        "feedback": {
          "alert-primary": {
            "type": "color",
            "value": "{colors.red.500}"
          },
          "alert-secondary": {
            "type": "color",
            "value": "{colors.red.300}"
          },
          "alert-tertiary": {
            "type": "color",
            "value": "{colors.red.50}"
          },
          "info-primary": {
            "type": "color",
            "value": "{colors.blue.500}"
          },
          "info-secondary": {
            "type": "color",
            "value": "{colors.blue.300}"
          },
          "info-tertiary": {
            "type": "color",
            "value": "{colors.blue.100}"
          },
          "success-primary": {
            "type": "color",
            "value": "{colors.green.500}"
          },
          "success-secondary": {
            "type": "color",
            "value": "{colors.green.300}"
          },
          "success-tertiary": {
            "type": "color",
            "value": "{colors.green.100}"
          },
          "warning-primary": {
            "type": "color",
            "value": "{colors.yellow.500}"
          },
          "warning-secondary": {
            "type": "color",
            "value": "{colors.yellow.300}"
          },
          "warning-tertiary": {
            "type": "color",
            "value": "{colors.yellow.100}"
          }
        },
        "inverse": {
          "default": {
            "type": "color",
            "value": "{colors.neutral.900}"
          },
          "tint-70": {
            "type": "color",
            "value": "{colors.neutral.alpha.900.70}"
          }
        },
        "neutral": {
          "black": {
            "type": "color",
            "value": "{colors.neutral.black}"
          },
          "white": {
            "type": "color",
            "value": "{colors.neutral.white}"
          }
        },
        "overlay": {
          "primary": {
            "type": "color",
            "value": "{colors.neutral.alpha.black.20}"
          },
          "quarternary": {
            "type": "color",
            "value": "{colors.neutral.alpha.black.2}"
          },
          "secondary": {
            "type": "color",
            "value": "{colors.neutral.alpha.900.10}"
          },
          "tertiarty": {
            "type": "color",
            "value": "{colors.neutral.white}"
          }
        },
        "placeholder": {
          "default": {
            "type": "color",
            "value": "{colors.neutral.50}"
          }
        },
        "primary": {
          "active": {
            "type": "color",
            "value": "{colors.neutral.200}"
          },
          "active-alt": {
            "type": "color",
            "value": "{colors.neutral.600}"
          },
          "default": {
            "type": "color",
            "value": "{colors.neutral.50}"
          },
          "hover": {
            "type": "color",
            "value": "{colors.neutral.100}"
          },
          "tint-50": {
            "type": "color",
            "value": "{colors.neutral.alpha.50.50}"
          },
          "tint-90": {
            "type": "color",
            "value": "{colors.neutral.alpha.50.90}"
          }
        },
        "quaternary": {
          "active": {
            "type": "color",
            "value": "{colors.neutral.300}"
          },
          "default": {
            "type": "color",
            "value": "{colors.neutral.200}"
          },
          "hover": {
            "type": "color",
            "value": "{colors.neutral.300}"
          }
        },
        "secondary": {
          "active": {
            "type": "color",
            "value": "{colors.neutral.100}"
          },
          "default": {
            "type": "color",
            "value": "{colors.neutral.white}"
          },
          "hover": {
            "type": "color",
            "value": "{colors.neutral.alpha.100.50}"
          }
        },
        "tertiary": {
          "active": {
            "type": "color",
            "value": "{colors.neutral.200}"
          },
          "default": {
            "type": "color",
            "value": "{colors.neutral.100}"
          },
          "hover": {
            "type": "color",
            "value": "{colors.neutral.200}"
          }
        }
      },
      "border": {
        "disabled": {
          "type": "color",
          "value": "{colors.neutral.200}"
        },
        "disabled-alt": {
          "type": "color",
          "value": "{colors.neutral.300}"
        },
        "fade": {
          "type": "color",
          "value": "{colors.neutral.alpha.900.10}"
        },
        "feedback": {
          "alert-primary": {
            "type": "color",
            "value": "{colors.brand.primary.100}"
          },
          "alert-secondary": {
            "type": "color",
            "value": "{fg.feedback.alert-primary}"
          },
          "info-primary": {
            "type": "color",
            "value": "{colors.blue.100}"
          },
          "info-secondary": {
            "type": "color",
            "value": "{fg.feedback.nfo-primary}"
          },
          "success-primary": {
            "type": "color",
            "value": "{colors.green.100}"
          },
          "success-secondary": {
            "type": "color",
            "value": "{fg.feedback.success-primary}"
          },
          "warning-primary": {
            "type": "color",
            "value": "{colors.yellow.100}"
          },
          "warning-secondary": {
            "type": "color",
            "value": "{fg.feedback.warning-primary}"
          }
        },
        "placeholder": {
          "type": "color",
          "value": "{colors.neutral.400}"
        },
        "primary": {
          "type": "color",
          "value": "{colors.neutral.200}"
        },
        "primary-active": {
          "type": "color",
          "value": "{colors.neutral.300}"
        },
        "primary-active-alt": {
          "type": "color",
          "value": "{colors.neutral.900}"
        },
        "secondary": {
          "type": "color",
          "value": "{colors.neutral.300}"
        },
        "secondary-active": {
          "type": "color",
          "value": "{colors.neutral.400}"
        }
      },
      "effects": {
        "shadows": {
          "lg": {
            "type": "color",
            "value": "{colors.neutral.alpha.950.20}"
          },
          "md": {
            "type": "color",
            "value": "{colors.neutral.alpha.950.10}"
          },
          "sm": {
            "type": "color",
            "value": "{colors.neutral.alpha.950.5}"
          },
          "xl": {
            "type": "color",
            "value": "{colors.neutral.alpha.950.50}"
          }
        }
      },
      "fg": {
        "brand": {
          "default": {
            "type": "color",
            "value": "{colors.brand.primary.300}"
          },
          "gradient": {
            "from": {
              "type": "color",
              "value": "{colors.brand.gradients.gradient-from}"
            },
            "to": {
              "type": "color",
              "value": "{colors.brand.gradients.gradient-to}"
            }
          }
        },
        "disabled": {
          "default": {
            "type": "color",
            "value": "{colors.neutral.300}"
          }
        },
        "feedback": {
          "alert-primary": {
            "type": "color",
            "value": "{colors.red.500}"
          },
          "alert-secondary": {
            "type": "color",
            "value": "{colors.red.100}"
          },
          "info-secondary": {
            "type": "color",
            "value": "{colors.blue.100}"
          },
          "nfo-primary": {
            "type": "color",
            "value": "{colors.blue.500}"
          },
          "success-primary": {
            "type": "color",
            "value": "{colors.green.500}"
          },
          "success-secondary": {
            "type": "color",
            "value": "{colors.green.200}"
          },
          "warning-primary": {
            "type": "color",
            "value": "{colors.yellow.500}"
          },
          "warning-secondary": {
            "type": "color",
            "value": "{colors.yellow.200}"
          }
        },
        "inverse": {
          "default": {
            "type": "color",
            "value": "{colors.neutral.white}"
          }
        },
        "neutral": {
          "black": {
            "type": "color",
            "value": "{colors.neutral.black}"
          },
          "white": {
            "type": "color",
            "value": "{colors.neutral.white}"
          }
        },
        "placeholder": {
          "default": {
            "type": "color",
            "value": "{colors.neutral.400}"
          }
        },
        "primary": {
          "default": {
            "type": "color",
            "value": "{colors.neutral.950}"
          }
        },
        "secondary": {
          "default": {
            "type": "color",
            "value": "{colors.neutral.700}"
          }
        },
        "tertiary": {
          "default": {
            "type": "color",
            "value": "{colors.neutral.500}"
          }
        }
      },
      "icons": {
        "primary": {
          "default": {
            "type": "color",
            "value": "{components.icons.primary.default}"
          },
          "default-fade": {
            "type": "color",
            "value": "{components.icons.primary.default-fade}"
          }
        },
        "secondary": {
          "default-fadeNEW": {
            "type": "color",
            "value": "{components.icons.secondary.darkmode-gradient}"
          },
          "defaultNEW": {
            "type": "color",
            "value": "{components.icons.secondary.default}"
          }
        }
      }
    },
    "dark": {
      "bg": {
        "brand": {
          "accent": {
            "type": "color",
            "value": "{colors.brand.secondary.300}"
          },
          "primary": {
            "type": "color",
            "value": "{colors.brand.primary.300}"
          },
          "secondary": {
            "type": "color",
            "value": "{colors.brand.accent1.3002}"
          }
        },
        "disabled": {
          "primary": {
            "type": "color",
            "value": "{colors.neutral.alpha.white.20}"
          },
          "secondary": {
            "type": "color",
            "value": "{colors.neutral.alpha.50.20}"
          }
        },
        "feedback": {
          "alert-primary": {
            "type": "color",
            "value": "{colors.red.500}"
          },
          "alert-secondary": {
            "type": "color",
            "value": "{colors.red.100}"
          },
          "alert-tertiary": {
            "type": "color",
            "value": "{colors.red.alpha.30030}"
          },
          "info-primary": {
            "type": "color",
            "value": "{colors.blue.500}"
          },
          "info-secondary": {
            "type": "color",
            "value": "{colors.blue.300}"
          },
          "info-tertiary": {
            "type": "color",
            "value": "{colors.blue.alpha.30030}"
          },
          "success-primary": {
            "type": "color",
            "value": "{colors.green.500}"
          },
          "success-secondary": {
            "type": "color",
            "value": "{colors.green.alpha.30050}"
          },
          "success-tertiary": {
            "type": "color",
            "value": "{colors.green.alpha.30030}"
          },
          "warning-primary": {
            "type": "color",
            "value": "{colors.yellow.500}"
          },
          "warning-secondary": {
            "type": "color",
            "value": "{colors.yellow.100}"
          },
          "warning-tertiary": {
            "type": "color",
            "value": "{colors.yellow.alpha.30030}"
          }
        },
        "inverse": {
          "default": {
            "type": "color",
            "value": "{colors.neutral.white}"
          },
          "tint-70": {
            "type": "color",
            "value": "{colors.neutral.alpha.white.70}"
          }
        },
        "neutral": {
          "black": {
            "type": "color",
            "value": "{colors.neutral.black}"
          },
          "white": {
            "type": "color",
            "value": "{colors.neutral.white}"
          }
        },
        "overlay": {
          "primary": {
            "type": "color",
            "value": "{colors.neutral.alpha.white.20}"
          },
          "quarternary": {
            "type": "color",
            "value": "{colors.neutral.alpha.white.2}"
          },
          "secondary": {
            "type": "color",
            "value": "{colors.neutral.alpha.50.20}"
          },
          "tertiarty": {
            "type": "color",
            "value": "{colors.neutral.alpha.white.70}"
          }
        },
        "placeholder": {
          "default": {
            "type": "color",
            "value": "{colors.neutral.900}"
          }
        },
        "primary": {
          "active": {
            "type": "color",
            "value": "{colors.neutral.800}"
          },
          "active-alt": {
            "type": "color",
            "value": "{colors.neutral.600}"
          },
          "default": {
            "type": "color",
            "value": "{colors.neutral.950}"
          },
          "hover": {
            "type": "color",
            "value": "{colors.neutral.800}"
          },
          "tint-50": {
            "type": "color",
            "value": "{colors.neutral.alpha.900.50}"
          },
          "tint-90": {
            "type": "color",
            "value": "{colors.neutral.alpha.900.90}"
          }
        },
        "quaternary": {
          "active": {
            "type": "color",
            "value": "{colors.neutral.700}"
          },
          "default": {
            "type": "color",
            "value": "{colors.neutral.700}"
          },
          "hover": {
            "type": "color",
            "value": "{colors.neutral.700}"
          }
        },
        "secondary": {
          "active": {
            "type": "color",
            "value": "{colors.neutral.700}"
          },
          "default": {
            "type": "color",
            "value": "{colors.neutral.900}"
          },
          "hover": {
            "type": "color",
            "value": "{colors.neutral.800}"
          }
        },
        "tertiary": {
          "active": {
            "type": "color",
            "value": "{colors.neutral.700}"
          },
          "default": {
            "type": "color",
            "value": "{colors.neutral.800}"
          },
          "hover": {
            "type": "color",
            "value": "{colors.neutral.700}"
          }
        }
      },
      "border": {
        "disabled": {
          "type": "color",
          "value": "{colors.neutral.700}"
        },
        "disabled-alt": {
          "type": "color",
          "value": "{colors.neutral.600}"
        },
        "fade": {
          "type": "color",
          "value": "{colors.neutral.alpha.50.10}"
        },
        "feedback": {
          "alert-primary": {
            "type": "color",
            "value": "{colors.brand.primary.400}"
          },
          "alert-secondary": {
            "type": "color",
            "value": "{fg.feedback.alert-primary}"
          },
          "info-primary": {
            "type": "color",
            "value": "{colors.blue.400}"
          },
          "info-secondary": {
            "type": "color",
            "value": "{fg.feedback.nfo-primary}"
          },
          "success-primary": {
            "type": "color",
            "value": "{colors.green.400}"
          },
          "success-secondary": {
            "type": "color",
            "value": "{fg.feedback.success-primary}"
          },
          "warning-primary": {
            "type": "color",
            "value": "{colors.yellow.400}"
          },
          "warning-secondary": {
            "type": "color",
            "value": "{fg.feedback.warning-primary}"
          }
        },
        "placeholder": {
          "type": "color",
          "value": "{colors.neutral.400}"
        },
        "primary": {
          "type": "color",
          "value": "{colors.neutral.700}"
        },
        "primary-active": {
          "type": "color",
          "value": "{colors.neutral.600}"
        },
        "primary-active-alt": {
          "type": "color",
          "value": "{colors.neutral.400}"
        },
        "secondary": {
          "type": "color",
          "value": "{colors.neutral.600}"
        },
        "secondary-active": {
          "type": "color",
          "value": "{colors.neutral.500}"
        }
      },
      "effects": {
        "shadows": {
          "lg": {
            "type": "color",
            "value": "{colors.neutral.alpha.50.20}"
          },
          "md": {
            "type": "color",
            "value": "{colors.neutral.alpha.50.10}"
          },
          "sm": {
            "type": "color",
            "value": "{colors.neutral.alpha.50.5}"
          },
          "xl": {
            "type": "color",
            "value": "{colors.neutral.alpha.50.50}"
          }
        }
      },
      "fg": {
        "brand": {
          "default": {
            "type": "color",
            "value": "{colors.brand.primary.300}"
          },
          "gradient": {
            "from": {
              "type": "color",
              "value": "{colors.brand.gradients.gradient-from}"
            },
            "to": {
              "type": "color",
              "value": "{colors.brand.gradients.gradient-to}"
            }
          }
        },
        "disabled": {
          "default": {
            "type": "color",
            "value": "{colors.neutral.500}"
          }
        },
        "feedback": {
          "alert-primary": {
            "type": "color",
            "value": "{colors.red.alpha.20090}"
          },
          "alert-secondary": {
            "type": "color",
            "value": "{colors.red.50}"
          },
          "info-secondary": {
            "type": "color",
            "value": "{colors.blue.100}"
          },
          "nfo-primary": {
            "type": "color",
            "value": "{colors.blue.100}"
          },
          "success-primary": {
            "type": "color",
            "value": "{colors.green.alpha.20080}"
          },
          "success-secondary": {
            "type": "color",
            "value": "{colors.green.100}"
          },
          "warning-primary": {
            "type": "color",
            "value": "{colors.yellow.alpha.20090}"
          },
          "warning-secondary": {
            "type": "color",
            "value": "{colors.yellow.100}"
          }
        },
        "inverse": {
          "default": {
            "type": "color",
            "value": "{colors.neutral.950}"
          }
        },
        "neutral": {
          "black": {
            "type": "color",
            "value": "{colors.neutral.black}"
          },
          "white": {
            "type": "color",
            "value": "{colors.neutral.white}"
          }
        },
        "placeholder": {
          "default": {
            "type": "color",
            "value": "{colors.neutral.400}"
          }
        },
        "primary": {
          "default": {
            "type": "color",
            "value": "{colors.neutral.100}"
          }
        },
        "secondary": {
          "default": {
            "type": "color",
            "value": "{colors.neutral.300}"
          }
        },
        "tertiary": {
          "default": {
            "type": "color",
            "value": "{colors.neutral.400}"
          }
        }
      },
      "icons": {
        "primary": {
          "default": {
            "type": "color",
            "value": "{components.icons.primary.darkmode}"
          },
          "default-fade": {
            "type": "color",
            "value": "{components.icons.primary.darkmode-fade}"
          }
        },
        "secondary": {
          "default-fadeNEW": {
            "type": "color",
            "value": "{components.icons.secondary.darkmode-gradient}"
          },
          "defaultNEW": {
            "type": "color",
            "value": "{components.icons.secondary.darkmode}"
          }
        }
      }
    }
  }
}